{
  "version": "1.0.3",
  "notes": "Seedream 4.5 v1.0.3（2026-05-30）",
  "downloadUrl": "https://ghfast.top/https://github.com/jiangheyou/seedream-desktop/releases/download/1.03/Seedream.4.5.Setup.1.0.3.exe",
  "fallbackUrls": [
    "https://github.com/jiangheyou/seedream-desktop/releases/download/1.03/Seedream.4.5.Setup.1.0.3.exe",
    "https://cdn.jsdelivr.net/gh/jiangheyou/seedream-desktop@main/dist/Seedream%204.5%20Setup%201.0.3.exe"
  ],
  "force": false,
  "releaseDate": "2026-05-30",
  "installer": true
}
